spawneditor.py
spawneditor-0.1.2.dist-info/LICENSE
spawneditor-0.1.2.dist-info/METADATA
spawneditor-0.1.2.dist-info/WHEEL
spawneditor-0.1.2.dist-info/top_level.txt
spawneditor-0.1.2.dist-info/RECORD
