Metadata-Version: 2.1
Name: spawneditor
Version: 0.1.2
Summary: Attempts to open a file at a specified line in the default editor.
Home-page: https://github.com/jamesderlin/python-spawneditor
Author: James D. Lin
Project-URL: Bug Reports, https://github.com/jamesderlin/python-spawneditor/issues
Classifier: Development Status :: 5 - Production/Stable
Classifier: Intended Audience :: Developers
Classifier: Topic :: Software Development :: Libraries
Classifier: License :: OSI Approved :: MIT License
Classifier: Operating System :: OS Independent
Classifier: Programming Language :: Python :: 3
Classifier: Programming Language :: Python :: 3 :: Only
Requires-Python: >=3.6
License-File: LICENSE
